{
  "name": "NynorskClearspeakFencesNeutral",
  "locale": "nn",
  "factory": "clearspeak",
  "base": "input/common/fences_neutral.json",
  "information": "Nynorsk Clearspeak Neutral Fences rule tests.",
  "active": "ClearspeakNynorsk",
  "exclude": [
    "BarFenced_0_sbrief",
    "BarFenced_1_sbrief",
    "BarFenced_2_sbrief",
    "BarFenced_3_sbrief",
    "BarFenced_4_sbrief",
    "BarFenced_5_sbrief",
    "BarFenced_6_sbrief",
    "BarFencedMixed_0_sbrief",
    "BarFencedMixed_1_sbrief",
    "BarFencedMixed_2_sbrief",
    "BarFencedMixed_3_sbrief",
    "CenterBar_0_sbrief",
    "CenterBar_1_sbrief",
    "CenterBar_2_sbrief",
    "CenterBar_3_sbrief",
    "CenterBar_4_sbrief",
    "CenterBar_5_sbrief",
    "Function_0_sbrief",
    "Function_1_sbrief",
    "Function_2_sbrief",
    "Function_3_sbrief",
    "Function_4_sbrief",
    "Function_5_sbrief",
    "FunctionMetric0_sbrief",
    "FunctionMetric1_sbrief",
    "FunctionMetric2_sbrief",
    "FunctionMetric3_sbrief",
    "FunctionMetric4_sbrief",
    "FunctionMetric5_sbrief",
    "CenterBarFunc_0_sbrief",
    "CenterBarFunc_1_sbrief",
    "CenterBarFunc_2_sbrief",
    "CenterBarFunc_3_sbrief",
    "CenterBarFunc_4_sbrief",
    "CenterBarFunc_5_sbrief",
    "CenterBarFunc_6_sbrief"
  ],
  "compare": true,
  "tests": {
    "BarFenced_0_default": {
      "expected": "the absolute value of a-th"
    },
    "BarFenced_1_default": {
      "expected": "the absolute value of a-th"
    },
    "BarFenced_2_default": {
      "expected": "the absolute value of a-th"
    },
    "BarFenced_3_default": {
      "expected": "the metric of a-th"
    },
    "BarFenced_4_default": {
      "expected": "the metric of a-th"
    },
    "BarFenced_5_default": {
      "expected": "the metric of a-th"
    },
    "BarFenced_6_default": {
      "expected": "the metric of a-th"
    },
    "BarFencedMixed_0_default": {
      "expected": "divides a-th dobbel vertikal strek"
    },
    "BarFencedMixed_1_default": {
      "expected": "parallell til a-th dobbel vertikal strek"
    },
    "BarFencedMixed_2_default": {
      "expected": "divides a-th divides"
    },
    "BarFencedMixed_3_default": {
      "expected": "trippel vertikalstrek-avgrensing a-th dobbel vertikal strek"
    },
    "CenterBar_0_default": {
      "expected": "a-th divides b-th"
    },
    "CenterBar_1_default": {
      "expected": "a-th divides b-th"
    },
    "CenterBar_2_default": {
      "expected": "a-th divides b-th"
    },
    "CenterBar_3_default": {
      "expected": "a-th dobbel vertikal strek b-th"
    },
    "CenterBar_4_default": {
      "expected": "a-th parallell til b-th"
    },
    "CenterBar_5_default": {
      "expected": "a-th trippel vertikalstrek-avgrensing b-th"
    },
    "CenterBarFunc_0_default": {
      "expected": "f-th divides g-th"
    },
    "CenterBarFunc_1_default": {
      "expected": "f-th divides g-th"
    },
    "CenterBarFunc_2_default": {
      "expected": "f-th divides g-th"
    },
    "CenterBarFunc_3_default": {
      "expected": "f-th dobbel vertikal strek g-th"
    },
    "CenterBarFunc_4_default": {
      "expected": "f-th parallell til g-th"
    },
    "CenterBarFunc_5_default": {
      "expected": "f-th trippel vertikalstrek-avgrensing g-th"
    },
    "CenterBarFunc_6_default": {
      "expected": "sinus trippel vertikalstrek-avgrensing g-th"
    },
    "Function_0_default": {
      "expected": "f-th of, the absolute value of a-th"
    },
    "Function_1_default": {
      "expected": "g-th of, the absolute value of a-th"
    },
    "Function_2_default": {
      "expected": "h-th of, the absolute value of a-th"
    },
    "Function_3_default": {
      "expected": "r-th ganger, the absolute value of a-th"
    },
    "Function_4_default": {
      "expected": "sinus, the absolute value of a-th"
    },
    "Function_5_default": {
      "expected": "sum of, the absolute value of a-th"
    },
    "FunctionMetric0_default": {
      "expected": "f-th of, the metric of a-th"
    },
    "FunctionMetric1_default": {
      "expected": "g-th of, the metric of a-th"
    },
    "FunctionMetric2_default": {
      "expected": "h-th of, the metric of a-th"
    },
    "FunctionMetric3_default": {
      "expected": "r-th ganger, the metric of a-th"
    },
    "FunctionMetric4_default": {
      "expected": "sinus, the metric of a-th"
    },
    "FunctionMetric5_default": {
      "expected": "sum of, the metric of a-th"
    },
    "BarFenced_0_AbsoluteValue_AbsEnd": {
      "expected": "the absolute value of a-th, end absolute value"
    },
    "BarFenced_1_AbsoluteValue_AbsEnd": {
      "expected": "the absolute value of a-th, end absolute value"
    },
    "BarFenced_2_AbsoluteValue_AbsEnd": {
      "expected": "the absolute value of a-th, end absolute value"
    },
    "BarFenced_3_AbsoluteValue_AbsEnd": {
      "expected": "the metric of a-th, end metric"
    },
    "BarFenced_4_AbsoluteValue_AbsEnd": {
      "expected": "the metric of a-th, end metric"
    },
    "BarFenced_5_AbsoluteValue_AbsEnd": {
      "expected": "the metric of a-th, end metric"
    },
    "BarFenced_6_AbsoluteValue_AbsEnd": {
      "expected": "the metric of a-th, end metric"
    },
    "BarFencedMixed_0_AbsoluteValue_AbsEnd": {
      "expected": "divides a-th dobbel vertikal strek"
    },
    "BarFencedMixed_1_AbsoluteValue_AbsEnd": {
      "expected": "parallell til a-th dobbel vertikal strek"
    },
    "BarFencedMixed_2_AbsoluteValue_AbsEnd": {
      "expected": "divides a-th divides"
    },
    "BarFencedMixed_3_AbsoluteValue_AbsEnd": {
      "expected": "trippel vertikalstrek-avgrensing a-th dobbel vertikal strek"
    },
    "CenterBar_0_AbsoluteValue_AbsEnd": {
      "expected": "a-th divides b-th"
    },
    "CenterBar_1_AbsoluteValue_AbsEnd": {
      "expected": "a-th divides b-th"
    },
    "CenterBar_2_AbsoluteValue_AbsEnd": {
      "expected": "a-th divides b-th"
    },
    "CenterBar_3_AbsoluteValue_AbsEnd": {
      "expected": "a-th dobbel vertikal strek b-th"
    },
    "CenterBar_4_AbsoluteValue_AbsEnd": {
      "expected": "a-th parallell til b-th"
    },
    "CenterBar_5_AbsoluteValue_AbsEnd": {
      "expected": "a-th trippel vertikalstrek-avgrensing b-th"
    },
    "Function_0_AbsoluteValue_AbsEnd": {
      "expected": "f-th of, the absolute value of a-th, end absolute value"
    },
    "Function_1_AbsoluteValue_AbsEnd": {
      "expected": "g-th of, the absolute value of a-th, end absolute value"
    },
    "Function_2_AbsoluteValue_AbsEnd": {
      "expected": "h-th of, the absolute value of a-th, end absolute value"
    },
    "Function_3_AbsoluteValue_AbsEnd": {
      "expected": "r-th ganger, the absolute value of a-th, end absolute value"
    },
    "Function_4_AbsoluteValue_AbsEnd": {
      "expected": "sinus, the absolute value of a-th, end absolute value"
    },
    "Function_5_AbsoluteValue_AbsEnd": {
      "expected": "sum of, the absolute value of a-th, end absolute value"
    },
    "FunctionMetric0_AbsoluteValue_AbsEnd": {
      "expected": "f-th of, the metric of a-th, end metric"
    },
    "FunctionMetric1_AbsoluteValue_AbsEnd": {
      "expected": "g-th of, the metric of a-th, end metric"
    },
    "FunctionMetric2_AbsoluteValue_AbsEnd": {
      "expected": "h-th of, the metric of a-th, end metric"
    },
    "FunctionMetric3_AbsoluteValue_AbsEnd": {
      "expected": "r-th ganger, the metric of a-th, end metric"
    },
    "FunctionMetric4_AbsoluteValue_AbsEnd": {
      "expected": "sinus, the metric of a-th, end metric"
    },
    "FunctionMetric5_AbsoluteValue_AbsEnd": {
      "expected": "sum of, the metric of a-th, end metric"
    },
    "CenterBarFunc_0_AbsoluteValue_AbsEnd": {
      "expected": "f-th divides g-th"
    },
    "CenterBarFunc_1_AbsoluteValue_AbsEnd": {
      "expected": "f-th divides g-th"
    },
    "CenterBarFunc_2_AbsoluteValue_AbsEnd": {
      "expected": "f-th divides g-th"
    },
    "CenterBarFunc_3_AbsoluteValue_AbsEnd": {
      "expected": "f-th dobbel vertikal strek g-th"
    },
    "CenterBarFunc_4_AbsoluteValue_AbsEnd": {
      "expected": "f-th parallell til g-th"
    },
    "CenterBarFunc_5_AbsoluteValue_AbsEnd": {
      "expected": "f-th trippel vertikalstrek-avgrensing g-th"
    },
    "CenterBarFunc_6_AbsoluteValue_AbsEnd": {
      "expected": "sinus trippel vertikalstrek-avgrensing g-th"
    }
  }
}
